crypto_com/__init__.py
crypto_com/crypto_com.py
crypto_com_client-1.2.dist-info/LICENSE
crypto_com_client-1.2.dist-info/WHEEL
crypto_com_client-1.2.dist-info/METADATA
crypto_com_client-1.2.dist-info/RECORD
