Metadata-Version: 2.1
Name: crypto-com-client
Version: 1.2
Summary: Crypto.com websocket api client
Home-page: https://github.com/maxpowel/crypto_com_client
License: Apache-2.0
Keywords: websocket,client,crypto
Author: Alvaro Garcia
Author-email: maxpowel@gmail.com
Requires-Python: >=3.8
Classifier: License :: OSI Approved :: Apache Software License
Classifier: Programming Language :: Python :: 3
Classifier: Programming Language :: Python :: 3.8
Classifier: Programming Language :: Python :: 3.9
Classifier: Topic :: Adaptive Technologies
Classifier: Topic :: Software Development
Classifier: Topic :: System
Classifier: Topic :: Utilities
Requires-Dist: orjson (>=3,<4)
Requires-Dist: websockets (>=12,<13)
Project-URL: Documentation, https://github.com/maxpowel/crypto_com_client
Project-URL: Repository, https://github.com/maxpowel/crypto_com_client
